[
    {
        "name": "Manage Sauron",
        "slug": "sauron-manage-all",
        "description": "Allows user to perform all actions on Sauron app",
        "permissions": {
            "entities": {
                "Apps\\Sauron\\Php\\Entities\\Rule": {
                    "crudCreate": true,
                    "crudRead": true,
                    "crudUpdate": true,
                    "crudDelete": true
                },
                "Apps\\Sauron\\Php\\Entities\\ScoreCard": {
                    "crudCreate": true,
                    "crudRead": true,
                    "crudUpdate": true,
                    "crudDelete": true,
                    "user/{user}": {
                        "get": true
                    }
                }
            }
        }
    }
]